LICENSE.txt
README.install
defsetup.py
distribute_setup.py
setup.cfg
setup.py
docs/Makefile
docs/make.bat
docs/source/conf.py
docs/source/displaydev.rst
docs/source/ichar.rst
docs/source/imconfig.rst
docs/source/index.rst
docs/source/numdisplay.rst
docs/source/overlay.rst
docs/source/zscale.rst
lib/stsci/__init__.py
lib/stsci.numdisplay.egg-info/PKG-INFO
lib/stsci.numdisplay.egg-info/SOURCES.txt
lib/stsci.numdisplay.egg-info/dependency_links.txt
lib/stsci.numdisplay.egg-info/namespace_packages.txt
lib/stsci.numdisplay.egg-info/not-zip-safe
lib/stsci.numdisplay.egg-info/requires.txt
lib/stsci.numdisplay.egg-info/top_level.txt
lib/stsci/numdisplay/__init__.py
lib/stsci/numdisplay/displaydev.py
lib/stsci/numdisplay/ichar.dat
lib/stsci/numdisplay/ichar.py
lib/stsci/numdisplay/imconfig.py
lib/stsci/numdisplay/imtoolrc
lib/stsci/numdisplay/overlay.py
lib/stsci/numdisplay/version.py
lib/stsci/numdisplay/zscale.py